custom_cloud_secret_manager_backend_kasna/__init__.py
custom_cloud_secret_manager_backend_kasna-1.0.0.dist-info/METADATA
custom_cloud_secret_manager_backend_kasna-1.0.0.dist-info/WHEEL
custom_cloud_secret_manager_backend_kasna-1.0.0.dist-info/RECORD
