Metadata-Version: 2.1
Name: custom_cloud_secret_manager_backend_kasna
Version: 1.0.0
Requires-Dist: apache-airflow
Requires-Dist: apache-airflow-providers-google
